{"label":"couchdemoshop","urlId":"clothes-shoes-and-jewelry","children":[{"label":"Genusswelten","urlId":"genusswelten","children":[{"label":"Tees und Zubeh\u00f6r","urlId":"genusswelten-tees-und-zubehoer","children":[{"label":"Tees","urlId":"genusswelten-tees-und-zubehoer-tees"},{"label":"Tee-Zubeh\u00f6r","urlId":"genusswelten-tees-und-zubehoer-tee-zubehoer"}]},{"label":"Edelbr\u00e4nde","urlId":"genusswelten-edelbraende"},{"label":"K\u00f6stlichkeiten","urlId":"genusswelten-koestlichkeiten"}]},{"label":"Sommerwelten","urlId":"sommerwelten","children":[{"label":"Beachwear","urlId":"sommerwelten-beachwear"},{"label":"Beauty & Care","urlId":"sommerwelten-beauty-und-care"},{"label":"On World Tour","urlId":"sommerwelten-on-world-tour"},{"label":"Accessoires","urlId":"sommerwelten-accessoires"}]},{"label":"Wohnwelten","urlId":"wohnwelten","children":[{"label":"M\u00f6bel","urlId":"wohnwelten-moebel"},{"label":"K\u00fcchenzubeh\u00f6r","urlId":"wohnwelten-kuechenzubehoer"},{"label":"Dekoration","urlId":"wohnwelten-dekoration"}]},{"label":"Freizeitwelten","urlId":"freizeitwelten","children":[{"label":"Entertainment","urlId":"freizeitwelten-entertainment"},{"label":"Vintage","urlId":"freizeitwelten-vintage"}]},{"label":"Beispiele","urlId":"beispiele","children":[{"label":"Crossselling","urlId":"beispiele-crossselling"},{"label":"Darstellung","urlId":"beispiele-darstellung"},{"label":"Produktvergleiche & Filter","urlId":"beispiele-produktvergleiche-und-filter"},{"label":"Konfiguratorartikel","urlId":"beispiele-konfiguratorartikel"},{"label":"Preisgestaltung","urlId":"beispiele-preisgestaltung"},{"label":"Versandkosten","urlId":"beispiele-versandkosten"},{"label":"Zahlungsarten","urlId":"beispiele-zahlungsarten"},{"label":"In K\u00fcrze verf\u00fcgbar","urlId":"beispiele-in-kuerze-verfuegbar"},{"label":"Kundenbindung","urlId":"beispiele-kundenbindung"},{"label":"Kundengruppen  \/  B2B","urlId":"beispiele-kundengruppen-b2b"}]},{"label":"% SALE","urlId":"sale"}]}