{"label":"haremdas","urlId":"clothes-shoes-and-jewelry","children":[{"label":"Jupes","urlId":"jupe-danse-orientale"},{"label":"Costumes","urlId":"costume-danse-orientale","children":[{"label":"Costumes 2 pi\u00e8ces","urlId":"costume-oriental-2-pieces"},{"label":"Costumes 3 pi\u00e8ces","urlId":"costume-oriental-3-pieces"},{"label":"Baladi","urlId":"robe-baladi"}]},{"label":"Hauts","urlId":"haut-danse-orientale","children":[{"label":"Bustier","urlId":"bustier"},{"label":"Cache coeur","urlId":"cache-coeur"},{"label":"Soutien-gorge","urlId":"soutien-gorge"},{"label":"Tops","urlId":"top"}]},{"label":"Sarouels","urlId":"sarouel-danse-orientale"},{"label":"Foulards","urlId":"foulard-danse-orientale","children":[{"label":"Foulards Triangle","urlId":"foulards-triangle"},{"label":"Foulards Rectangle","urlId":"foulards-rectangle"},{"label":"Foulards Demi cercle","urlId":"foulards-demi-cercle"},{"label":"Ceintures Metal","urlId":"ceintures-metal"}]},{"label":"Voiles","urlId":"voile-danse-orientale","children":[{"label":"Voiles Rectangle","urlId":"voile-rectangle"},{"label":"Voiles Demi lune","urlId":"voile-demi-lune"},{"label":"Brassards voile","urlId":"brassards-voile"}]},{"label":"Accessoires","urlId":"accessoires-danse-orientale"},{"label":"Bijoux","urlId":"bijoux-orientaux","children":[{"label":"Bijoux Indiens","urlId":"bijoux-indiens","children":[{"label":"Bijoux t\u00eate indien","urlId":"bijoux-tete-indien"},{"label":"Parure Bijoux","urlId":"parure-bijoux"},{"label":"Bijoux de main","urlId":"bijoux-de-main"},{"label":"Bijoux de nez","urlId":"bijoux-de-nez"},{"label":"Bracelet de bras","urlId":"bracelet-de-bras"},{"label":"Bracelet indien","urlId":"bracelet-indien"},{"label":"Tikka indien","urlId":"tikka-indien"},{"label":"Bracelet cheville","urlId":"bracelet-cheville"},{"label":"Bindi indien","urlId":"bindi-indien"}]}]}]}